README.md
setup.py
youtube_to_mp3.egg-info/PKG-INFO
youtube_to_mp3.egg-info/SOURCES.txt
youtube_to_mp3.egg-info/dependency_links.txt
youtube_to_mp3.egg-info/entry_points.txt
youtube_to_mp3.egg-info/top_level.txt
yturl2mp3/__init__.py
yturl2mp3/__main__.py
yturl2mp3/config.py
yturl2mp3/helpers.py
yturl2mp3/yturl2mp3.py