Metadata-Version: 2.1
Name: youtube-to-mp3
Version: 0.4.1
Summary: Download YouTube videos or playlists as MP3 audio files from a url.
Home-page: https://github.com/cedricouellet/youtube-to-mp3.git
Author: cedricao
Author-email: cedricao.noreply@gmail.com
License: UNKNOWN
Platform: UNKNOWN
